setup.py
bitfields/__init__.py
bitfields/bits.py
bitfields/fields.py
bitfields.egg-info/PKG-INFO
bitfields.egg-info/SOURCES.txt
bitfields.egg-info/dependency_links.txt
bitfields.egg-info/top_level.txt