Metadata-Version: 1.0
Name: bitfields
Version: 0.1
Summary: Bit manipulation library that allows binary number indexing and bit field construction.
Home-page: http://github.com/reshanie/bitfields
Author: Patrick Dill
Author-email: jamespatrickdill@gmail.com
License: MIT
Platform: UNKNOWN
